<?xml version="1.0" encoding="utf-8"?>
<node>
  <File>
    <Fullpath></Fullpath>
    <Filename>bass.dll</Filename>
    <Hash>c5b3059004e2c7631915ec044f4e6c63</Hash>
    <Byte>128181</Byte>
  </File>
  <File>
    <Fullpath></Fullpath>
    <Filename>bass_fx.dll</Filename>
    <Hash>e7f4494bdf7b1c49a303fe56c6b52dc9</Hash>
    <Byte>34392</Byte>
  </File>
  <File>
    <Fullpath></Fullpath>
    <Filename>gprp.asi</Filename>
    <Hash>125d11abd9a862acb123b5c8a3c5d1ad</Hash>
    <Byte>942592</Byte>
  </File>
  <File>
    <Fullpath></Fullpath>
    <Filename>gta_sa.exe</Filename>
    <Hash>2b5066bd4097ac2944ce6a9cf8fe5677</Hash>
    <Byte>14383616</Byte>
  </File>
  <File>
    <Fullpath></Fullpath>
    <Filename>samp.exe</Filename>
    <Hash>ba64bb37a1c6588fbca0075c3ddc4a2a</Hash>
    <Byte>412672</Byte>
  </File>
  <File>
    <Fullpath></Fullpath>
    <Filename>Updater.exe</Filename>
    <Hash>4ee4ff3e9bee92b3a0947ef02d70aa55</Hash>
    <Byte>649728</Byte>
  </File>
  <File>
    <Fullpath></Fullpath>
    <Filename>vorbisFile.dll</Filename>
    <Hash>90223f6248b55e0813687fe1b7277dd7</Hash>
    <Byte>53760</Byte>
  </File>
  <File>
    <Fullpath></Fullpath>
    <Filename>vorbisHooked.dll</Filename>
    <Hash>2b7b803311d2b228f065c45d13e1aeb2</Hash>
    <Byte>65536</Byte>
  </File>
  <File>
    <Fullpath>models\txd\gprp.txd</Fullpath>
    <Filename>gprp.txd</Filename>
    <Hash>6d0ae8afa5c9a21851f123e19ed2b30a</Hash>
    <Byte>3020832</Byte>
  </File>
</node>
